<?xml version="1.0" encoding="UTF-8" standalone="no"?>
<servico xmlns="http://servicos.gov.br/v3/schema" xmlns:xsi="http://www.w3.org/2001/XMLSchema-instance" xsi:schemaLocation="http://servicos.gov.br/v3/schema ../servico.xsd">
	<nome>Calculadora do Cidadão</nome>
	<sigla/>
	<contato/>
	<nomes-populares>
		<item>Não</item>
	</nomes-populares>
	<descricao>Executa cálculos financeiros, como os referentes a taxas de juros embutidas em compras a prazo, a índices diversos de atualização monetária ou a financiamentose aplicações. São suas funcionalidades: aplicação com depósitos regulares; financiamento com prestações fixas; valor futuro de um capital; correção de valores;Disponível para consulta online e também como aplicativo para celulares nas principais plataformas de mercado.</descricao>
	<gratuito>true</gratuito>
	<solicitantes>
		<solicitante>
			<tipo>Cidadãos e Famílias</tipo>
			<requisitos/>
		</solicitante>
		<solicitante>
			<tipo>Empresas privadas</tipo>
			<requisitos/>
		</solicitante>
		<solicitante>
			<tipo>Empresas públicas ou de economia mista</tipo>
			<requisitos/>
		</solicitante>
		<solicitante>
			<tipo>Pessoas jurídicas de direito privado sem fins lucrativos</tipo>
			<requisitos/>
		</solicitante>
		<solicitante>
			<tipo>Fundações e autarquias de direito público</tipo>
			<requisitos/>
		</solicitante>
		<solicitante>
			<tipo>Órgãos da administração direta</tipo>
			<requisitos/>
		</solicitante>
		<solicitante>
			<tipo>Estados e municípios</tipo>
			<requisitos/>
		</solicitante>
	</solicitantes>
	<segmentos-da-sociedade>
		<item>Cidadãos</item>
		<item>Empresas</item>
		<item>Órgãos e entidades públicas</item>
		<item>Demais segmentos (ONGs, organizações sociais, etc)</item>
	</segmentos-da-sociedade>
	<tempo-total-estimado>
		<descricao>Não se aplica \ Não é estimado ainda.</descricao>
	</tempo-total-estimado>
	<etapas>
		<etapa>
			<titulo>Usuário acessa o aplicativo e o utiliza, realizando seus próprios cálculos. Caso deseje o usuário pode responder a uma pesquisa de satisfação.No caso do aplicativo o usuário instala o aplicativo e o utiliza, realizando seus próprios cálculos. Caso deseje é possível avaliar o aplicativo nas lojas virtuais.Esse iteração é recorrente, já que o usuário pode realizar quantos cálculos desejar e retornar ao aplicativo ou site para fazer novos cálculos, sempre que desejar.</titulo>
			<descricao/>
			<documentos>
				<default>
					<item>Nenhum</item>
				</default>
			</documentos>
			<custos>
				<default/>
			</custos>
			<canais-de-prestacao>
				<default>
					<canal-de-prestacao tipo="web">
						<descricao>http://www.bcb.gov.br/calculadora/calculadoracidadao.asp</descricao>
					</canal-de-prestacao>
					<canal-de-prestacao tipo="aplicativo-movel">
						<descricao>A calculadora do cidadão está disponível para IOS, Android e Wind</descricao>
					</canal-de-prestacao>
				</default>
			</canais-de-prestacao>
		</etapa>
	</etapas>
	<orgao id="http://estruturaorganizacional.dados.gov.br/id/unidade-organizacional/89"/>
	<areas-de-interesse>
		<item>Administração </item>
		<item>Comércio e Serviços</item>
		<item>Economia e Finanças</item>
		<item>Educação</item>
	</areas-de-interesse>
	<palavras-chave/>
	<legislacoes/>
</servico>
