<?xml version="1.0" encoding="UTF-8" standalone="no"?>
<servico xmlns="http://servicos.gov.br/v3/schema" xmlns:xsi="http://www.w3.org/2001/XMLSchema-instance" xsi:schemaLocation="http://servicos.gov.br/v3/schema ../servico.xsd">
	<nome>Requerer cessão de uso de espécimes fósseis</nome>
	<sigla/>
	<contato/>
	<nomes-populares>
		<item>Cessão de fósseis para instituição  pública</item>
	</nomes-populares>
	<descricao>Análise e celebração de um Termo de Cessão de Uso de Espécimes Fósseis com a instituição pública interessada</descricao>
	<gratuito>true</gratuito>
	<solicitantes>
		<solicitante>
			<tipo>Empresas públicas ou de economia mista</tipo>
			<requisitos/>
		</solicitante>
		<solicitante>
			<tipo>Fundações e autarquias de direito público</tipo>
			<requisitos/>
		</solicitante>
		<solicitante>
			<tipo>Estados e municípios</tipo>
			<requisitos/>
		</solicitante>
	</solicitantes>
	<segmentos-da-sociedade>
		<item>Empresas</item>
		<item>Órgãos e entidades públicas</item>
	</segmentos-da-sociedade>
	<tempo-total-estimado>
		<entre min="31" max="60" unidade="dias-corridos"/>
		<descricao/>
	</tempo-total-estimado>
	<etapas>
		<etapa>
			<titulo>Solicitação de material fóssil</titulo>
			<descricao/>
			<documentos>
				<default>
					<item>Carteira de identidade</item>
					<item>Carteira de trabalho</item>
					<item>CNPJ</item>
					<item>Comprovante de endereço/residência</item>
					<item>Informar os seguintes dados: 1) nome da instituição e CNPJ; 2) endereço completo (com CEP) da instituição; 3) nome completo (por extenso) do Diretor/Reitor e seu RG; 4) telefone e-mail de contato.</item>
				</default>
			</documentos>
			<custos>
				<default/>
			</custos>
			<canais-de-prestacao>
				<default>
					<canal-de-prestacao tipo="email">
						<descricao>paleontologia@dnpm.gov.br</descricao>
					</canal-de-prestacao>
					<canal-de-prestacao tipo="postal">
						<descricao>DNPM - Departamento Nacional de Produção Mineral (Edifício Sede)
S.A.N. Quadra 01, Bloco B
CEP: 70041-903 - Brasília - DF</descricao>
					</canal-de-prestacao>
				</default>
			</canais-de-prestacao>
		</etapa>
		<etapa>
			<titulo>Assinatura do Termo de Cessão de uso de espécimes fósseis.</titulo>
			<descricao/>
			<documentos>
				<default>
					<item>Carteira de identidade</item>
					<item>Carteira de trabalho</item>
				</default>
			</documentos>
			<custos>
				<default/>
			</custos>
			<canais-de-prestacao>
				<default>
					<canal-de-prestacao tipo="presencial">
						<descricao>DNPM - Departamento Nacional de Produção Mineral
Endereço da Sede/Brasília ou da Superintendência (se for o caso).</descricao>
					</canal-de-prestacao>
					<canal-de-prestacao tipo="web">
						<descricao>www.dnpm.gov.br, no item Acesso à Informação, link Processos e Documentos: Usuários Externos.</descricao>
					</canal-de-prestacao>
					<canal-de-prestacao tipo="postal">
						<descricao>DNPM - Departamento Nacional de Produção Mineral
Endereço da Sede/Brasília ou da Superintendência (se for o caso).</descricao>
					</canal-de-prestacao>
				</default>
			</canais-de-prestacao>
		</etapa>
	</etapas>
	<orgao id="http://estruturaorganizacional.dados.gov.br/id/unidade-organizacional/1918"/>
	<areas-de-interesse>
		<item>Educação</item>
		<item>Pesquisa e Desenvolvimento</item>
	</areas-de-interesse>
	<palavras-chave/>
	<legislacoes/>
</servico>
