<?xml version="1.0" encoding="UTF-8" standalone="no"?>
<servico xmlns="http://servicos.gov.br/v3/schema" xmlns:xsi="http://www.w3.org/2001/XMLSchema-instance" xsi:schemaLocation="http://servicos.gov.br/v3/schema ../servico.xsd">
	<nome>Elaboração de Projetos de Estabilidade e Execução de Obras de Contenção de Encostas em Áreas Urbanas, no âmbito do Programa de Aceleração do Crescimento – PAC ENCOSTA.</nome>
	<sigla/>
	<contato/>
	<nomes-populares>
		<item>PAC CONTENÇÃO DE ENCOSTAS</item>
	</nomes-populares>
	<descricao>O usuário deseja apoio para a elaboração de Projetos e execução de Obras para prevenção em áreas de riscos de desastres naturais. O MCIDADES busca apoiar aos Estados, Municípios e Distrito Federal para execução de intervenções estruturantes (elaboração de projetos e execução de obras) com o objetivo de prevenir a ocorrência de desastres relacionados a movimento de massa (deslizamentos de encostas, erosão, corridas de massa/detritos e processos correlatos), por meio da contenção de encostas e taludes em áreas urbanas, principalmente assentamentos precários e suas áreas de risco.</descricao>
	<gratuito>false</gratuito>
	<solicitantes>
		<solicitante>
			<tipo>Cidadãos e Famílias</tipo>
			<requisitos/>
		</solicitante>
		<solicitante>
			<tipo>Estrangeiros</tipo>
			<requisitos/>
		</solicitante>
		<solicitante>
			<tipo>Empresas privadas</tipo>
			<requisitos/>
		</solicitante>
		<solicitante>
			<tipo>Empresas públicas ou de economia mista</tipo>
			<requisitos/>
		</solicitante>
		<solicitante>
			<tipo>Pessoas jurídicas de direito privado sem fins lucrativos</tipo>
			<requisitos/>
		</solicitante>
		<solicitante>
			<tipo>Fundações e autarquias de direito público</tipo>
			<requisitos/>
		</solicitante>
		<solicitante>
			<tipo>Órgãos da administração direta</tipo>
			<requisitos/>
		</solicitante>
		<solicitante>
			<tipo>Estados e municípios</tipo>
			<requisitos/>
		</solicitante>
	</solicitantes>
	<segmentos-da-sociedade>
		<item>Cidadãos</item>
		<item>Empresas</item>
		<item>Órgãos e entidades públicas</item>
		<item>Demais segmentos (ONGs, organizações sociais, etc)</item>
	</segmentos-da-sociedade>
	<tempo-total-estimado>
		<descricao>Não se aplica \ Não é estimado ainda.</descricao>
	</tempo-total-estimado>
	<etapas>
		<etapa>
			<titulo>Envio de proposta e apresentação e justificativa técnica da proposta enviada.</titulo>
			<descricao/>
			<documentos>
				<default>
					<item>Projetos básico de engenharia para execução de obras de Contenção de Encostas</item>
				</default>
			</documentos>
			<custos>
				<default/>
			</custos>
			<canais-de-prestacao>
				<default>
					<canal-de-prestacao tipo="presencial">
						<descricao>Ministério das Cidades</descricao>
					</canal-de-prestacao>
				</default>
			</canais-de-prestacao>
		</etapa>
	</etapas>
	<orgao id="http://estruturaorganizacional.dados.gov.br/id/unidade-organizacional/42672"/>
	<areas-de-interesse>
		<item>Urbanismo</item>
	</areas-de-interesse>
	<palavras-chave/>
	<legislacoes/>
</servico>
