<?xml version="1.0" encoding="UTF-8" standalone="no"?>
<servico xmlns="http://servicos.gov.br/v3/schema" xmlns:xsi="http://www.w3.org/2001/XMLSchema-instance" xsi:schemaLocation="http://servicos.gov.br/v3/schema ../servico.xsd">
	<nome>Obter a Gestão Municipal de Praias Urbanas</nome>
	<sigla/>
	<contato/>
	<nomes-populares>
		<item>Adesão à Gestão de Praias</item>
	</nomes-populares>
	<descricao>Este serviço permite aos Municípios requerer adesão à gestão de praias urbanas.</descricao>
	<gratuito>true</gratuito>
	<solicitantes>
		<solicitante>
			<tipo>Estados e municípios</tipo>
			<requisitos/>
		</solicitante>
	</solicitantes>
	<segmentos-da-sociedade>
		<item>Órgãos e entidades públicas</item>
	</segmentos-da-sociedade>
	<tempo-total-estimado>
		<descricao>Não se aplica \ Não é estimado ainda.</descricao>
	</tempo-total-estimado>
	<etapas>
		<etapa>
			<titulo>Preencher o requerimento e anexar os documentos requisitados no Portal de Atendimento da SPU.</titulo>
			<descricao/>
			<documentos>
				<default>
					<item>Termo de Adesão à Gestão de Praias e Termo de posse do prefeito</item>
				</default>
			</documentos>
			<custos>
				<default/>
			</custos>
			<canais-de-prestacao>
				<default>
					<canal-de-prestacao tipo="web">
						<descricao>http://www.patrimoniodetodos.gov.br/#/servicoGenericoSemRip?servico=107#dados-documentos</descricao>
					</canal-de-prestacao>
				</default>
			</canais-de-prestacao>
		</etapa>
	</etapas>
	<orgao id="http://estruturaorganizacional.dados.gov.br/id/unidade-organizacional/2981"/>
	<areas-de-interesse>
		<item>Administração </item>
	</areas-de-interesse>
	<palavras-chave/>
	<legislacoes/>
</servico>
